distribuPy/__init__.py
distribuPy/client.py
distribuPy/distribuPy.py
distribuPy-0.1.dev0.dist-info/DESCRIPTION.rst
distribuPy-0.1.dev0.dist-info/METADATA
distribuPy-0.1.dev0.dist-info/RECORD
distribuPy-0.1.dev0.dist-info/WHEEL
distribuPy-0.1.dev0.dist-info/metadata.json
distribuPy-0.1.dev0.dist-info/top_level.txt
