Metadata-Version: 2.0
Name: distribuPy
Version: 0.1.dev0
Summary: Distributes computation to several machines.
Home-page: https://github.com/houstonlucas/distribuPy
Author: Houston Lucas
Author-email: houstonlucas@nevada.unr.edu
License: UNKNOWN
Keywords: parallelism networking
Platform: UNKNOWN
